metabolism/Analyzer.py
metabolism/Classifier.py
metabolism/CorrelationAnalyzer.py
metabolism/DcmWorker.py
metabolism/Helper.py
metabolism/MetabolicNetworks.py
metabolism/Painter.py
metabolism/Segmentor.py
metabolism/StabilityTester.py
metabolism/WIBC.py
metabolism/__init__.py
metabolism/wimc.py
metabolism/MPUM/__init__.py
metabolism/MPUM/categories.py
metabolism/MPUM/datautils.py
metabolism/MPUM/download_weights.py
metabolism/MPUM/inference.py
metabolism/MPUM/mpummodel.py
metabolism/MPUM/tissueclip_RN101.pth
metabolism-0.9.107.dist-info/METADATA
metabolism-0.9.107.dist-info/WHEEL
metabolism-0.9.107.dist-info/top_level.txt
metabolism-0.9.107.dist-info/RECORD
