Metadata-Version: 2.4
Name: metabolism
Version: 0.9.107
Summary: Multi-organ metabolic analysis framework
Author-email: Yixin Chen <yixinchen0320@gmail.com>
Requires-Dist: SimpleITK>=2.2.1
Requires-Dist: pydicom>=2.2.2
Requires-Dist: dicom2nifti>=2.4.8
Requires-Dist: numpy==1.26.4
Requires-Dist: matplotlib
Requires-Dist: einops
Requires-Dist: monai==1.2.0
Requires-Dist: tqdm
Requires-Dist: nnunet==1.7.1
Requires-Dist: pandas
Requires-Dist: scipy
Requires-Dist: networkx
Requires-Dist: xgboost
Requires-Dist: scikit-learn
Requires-Dist: seaborn
